strast/__init__.py
strast/class_based.py
strast/core.py
strast/factory.py
strast-0.1.1.dist-info/LICENCE
strast-0.1.1.dist-info/METADATA
strast-0.1.1.dist-info/WHEEL
strast-0.1.1.dist-info/top_level.txt
strast-0.1.1.dist-info/RECORD
