Metadata-Version: 2.1
Name: strast
Version: 0.1.1
Summary: Transforms a string representation of a Python literal into the corresponding Python object.
Home-page: https://github.com/janthmueller/strast
Author: Jan T. Müller
Author-email: mail@jantmueller.com
License: MIT
Project-URL: Documentation, https://janthmueller.github.io/strast/docs/strast.html
Project-URL: Source, https://github.com/janthmueller/strast
Project-URL: Tracker, https://github.com/janthmueller/strast/issues
Platform: UNKNOWN
Classifier: Intended Audience :: Developers
Classifier: Topic :: Software Development :: Libraries :: Python Modules
Classifier: License :: OSI Approved :: MIT License
Classifier: Operating System :: OS Independent
Classifier: Programming Language :: Python :: 3 :: Only
Requires-Python: >=3.6
License-File: LICENCE
